PyChest.cp38-win_amd64.pyd
PyChestBuild/GoChest.darwin.amd64.so
PyChestBuild/GoChest.linux.386.so
PyChestBuild/GoChest.linux.amd64.so
PyChestBuild/GoChest.windows.386.dll
PyChestBuild/GoChest.windows.amd64.dll
PyChestBuild/__init__.py
PyChestBuild/identify.py
PyChest-1.2.dist-info/LICENSE.md
PyChest-1.2.dist-info/METADATA
PyChest-1.2.dist-info/WHEEL
PyChest-1.2.dist-info/top_level.txt
PyChest-1.2.dist-info/RECORD
