Metadata-Version: 2.1
Name: PyChest
Version: 1.2
Summary: Locating distributional changes in piece-wise stationary time-series with long-range dependencies
Home-page: UNKNOWN
Author: Lukas Zierahn
Author-email: lukas@kappa-mm.de
License: bsd-3-clause
Keywords: Changepoint Estimation,Dependent Data,Unknown Number of Change Points
Platform: UNKNOWN
Classifier: Development Status :: 5 - Production/Stable
Classifier: Intended Audience :: Developers
Classifier: Topic :: Software Development :: Build Tools
Classifier: License :: OSI Approved :: BSD License
Classifier: Programming Language :: Python :: 3
Requires-Dist: setuptools
Requires-Dist: Cython
